rltrade/__init__.py
rltrade/backtests.py
rltrade/config.py
rltrade/data.py
rltrade/environments.py
rltrade/ibkr.py
rltrade/models.py
rltrade_test-0.7.4.dist-info/METADATA
rltrade_test-0.7.4.dist-info/WHEEL
rltrade_test-0.7.4.dist-info/top_level.txt
rltrade_test-0.7.4.dist-info/RECORD
