Metadata-Version: 2.1
Name: rltrade-test
Version: 0.7.4
Summary: Easy to use Reinforcement Library for finance
Home-page: https://github.com/Bonobo791/rl-trade/
License: UNKNOWN
Keywords: Reinforcement Learning
Platform: UNKNOWN
Requires-Python: >=3.7
Requires-Dist: gym
Requires-Dist: torch
Requires-Dist: numpy
Requires-Dist: psutil
Requires-Dist: plotly
Requires-Dist: pandas
Requires-Dist: seaborn
Requires-Dist: lightgbm
Requires-Dist: yfinance
Requires-Dist: stockstats
Requires-Dist: matplotlib
Requires-Dist: statsmodels
Requires-Dist: tensorboard
Requires-Dist: pyfolio-reloaded
Requires-Dist: metaapi-cloud-sdk
Requires-Dist: rltrade-pypbo (==0.0.3)
Requires-Dist: stable-baselines3 (==1.3.0)
Requires-Dist: rltrade-ibapi (==9.76.1)
